ansible/module_utils/virl.py
ansible/modules/virl/virl_interface.py
ansible/modules/virl/virl_lab.py
ansible/modules/virl/virl_lab_facts.py
ansible/modules/virl/virl_node.py
ansible/plugins/inventory/virl.py
ansible/plugins/inventory/virl2.py
ansible_virl-0.0.7.dist-info/LICENSE
ansible_virl-0.0.7.dist-info/METADATA
ansible_virl-0.0.7.dist-info/WHEEL
ansible_virl-0.0.7.dist-info/top_level.txt
ansible_virl-0.0.7.dist-info/RECORD
